resilient_circuits/LICENSE
resilient_circuits/README
resilient_circuits/__init__.py
resilient_circuits/action_message.py
resilient_circuits/actions_component.py
resilient_circuits/actions_test_component.py
resilient_circuits/app.py
resilient_circuits/app_argument_parser.py
resilient_circuits/app_function_component.py
resilient_circuits/app_restartable.py
resilient_circuits/component_loader.py
resilient_circuits/constants.py
resilient_circuits/decorators.py
resilient_circuits/filters.py
resilient_circuits/helpers.py
resilient_circuits/keyring_arguments.py
resilient_circuits/rest_helper.py
resilient_circuits/stomp_component.py
resilient_circuits/stomp_events.py
resilient_circuits/stomp_transport.py
resilient_circuits/template_functions.py
resilient_circuits/validate_configs.py
resilient_circuits/bin/__init__.py
resilient_circuits/bin/res_action_test.py
resilient_circuits/bin/resilient_circuits_cmd.py
resilient_circuits/bin/service_wrapper.py
resilient_circuits/cmds/__init__.py
resilient_circuits/cmds/selftest.py
resilient_circuits/data/app.config.base
resilient_circuits/data/rest-api-adapter-service.yaml
resilient_circuits/data/rest-api-adapter-service_2.yaml
resilient_circuits/util/__init__.py
resilient_circuits/util/resilient_config.py
resilient_circuits/util/resilient_customize.py
resilient_circuits-51.0.7.2.16540.dist-info/METADATA
resilient_circuits-51.0.7.2.16540.dist-info/WHEEL
resilient_circuits-51.0.7.2.16540.dist-info/entry_points.txt
resilient_circuits-51.0.7.2.16540.dist-info/top_level.txt
resilient_circuits-51.0.7.2.16540.dist-info/RECORD
