Metadata-Version: 2.4
Name: resilient_circuits
Version: 51.0.7.2.16540
Summary: Framework used to run IBM SOAR Apps and Integrations
Home-page: https://github.com/ibmresilient/resilient-python-api/tree/main/resilient-circuits
Author: IBM SOAR
License: MIT
Project-URL: Documentation, https://ibm.biz/soar-python-docs
Project-URL: API Docs, https://ibm.biz/soar-python-docs
Project-URL: IBM Community, https://ibm.biz/soarcommunity
Project-URL: Change Log, https://ibm.biz/resilient-circuits-changes
Keywords: ibm,soar,resilient,resilient-circuits,circuits,resilient-sdk,sdk
Classifier: Programming Language :: Python :: 3.9
Classifier: Programming Language :: Python :: 3.11
Classifier: Programming Language :: Python :: 3.12
Requires-Python: >=3.9
Requires-Dist: resilient>=51.0.7.2
Requires-Dist: resilient-lib>=51.0.7.2
Requires-Dist: stomp-py~=8.2
Requires-Dist: circuits~=3.2.3
Requires-Dist: pysocks~=1.6
Requires-Dist: filelock~=3.2
Requires-Dist: watchdog~=2.1
